spamcheck/__init__.py
spamcheck-1.0.3.dist-info/DESCRIPTION.rst
spamcheck-1.0.3.dist-info/METADATA
spamcheck-1.0.3.dist-info/RECORD
spamcheck-1.0.3.dist-info/WHEEL
spamcheck-1.0.3.dist-info/metadata.json
spamcheck-1.0.3.dist-info/top_level.txt
