Metadata-Version: 2.0
Name: spamcheck
Version: 1.0.3
Summary: A simple Python wrapper for Postmark's Spamcheck API
Home-page: https://github.com/Tesorio/spamcheck-python
Author: Tesorio
Author-email: hello@tesorio.com
License: MIT License
Keywords: postmark spam spamcheck
Platform: UNKNOWN
Requires-Dist: requests
